sqllm/__init__.py
sqllm/_extract_table_names.py
sqllm/core.py
sqllm/functions.py
sqllm/version.py
tests/__init__.py
tests/test_core.py
tests/test_functions.py
sqllm-0.0.1.dist-info/LICENSE
sqllm-0.0.1.dist-info/METADATA
sqllm-0.0.1.dist-info/WHEEL
sqllm-0.0.1.dist-info/top_level.txt
sqllm-0.0.1.dist-info/RECORD
