Metadata-Version: 2.1
Name: sqllm
Version: 0.0.1
Summary: SQL with LLM
Home-page: https://github.com/nyanp/sqllm
Author: nyanp
Author-email: Noumi.Taiga@gmail.com
License: MIT
Keywords: llm sql
Classifier: License :: OSI Approved :: MIT License
Classifier: Programming Language :: Python :: 3.10
Classifier: Programming Language :: Python :: 3.11
License-File: LICENSE
Requires-Dist: duckdb
Requires-Dist: openai
Requires-Dist: pandas
Requires-Dist: sqlparse
